cpfpy/__init__.py
cpfpy/format_cpf.py
cpfpy/validate_cpf.py
cpfpy/utils/__init__.py
cpfpy/utils/digits.py
cpfpy-0.0.1.dist-info/METADATA
cpfpy-0.0.1.dist-info/WHEEL
cpfpy-0.0.1.dist-info/top_level.txt
cpfpy-0.0.1.dist-info/RECORD
