Metadata-Version: 2.1
Name: cpfpy
Version: 0.0.1
Summary: This Python module validates and formats CPF numbers, ensuring they are correct and follow the standard Brazilian format.
Home-page: https://github.com/adryansf/cpfpy
Author: Adryan Freitas
Author-email: adryansfreitas@gmail.com
Requires-Python: >=3.0
